clitool/__init__.py
clitool/ding.wav
clitool/github.py
gitloop-0.1.2.dist-info/licenses/LICENSE
gitloop-0.1.2.dist-info/METADATA
gitloop-0.1.2.dist-info/WHEEL
gitloop-0.1.2.dist-info/entry_points.txt
gitloop-0.1.2.dist-info/top_level.txt
gitloop-0.1.2.dist-info/RECORD
