Metadata-Version: 2.4
Name: Gitloop
Version: 0.1.2
Summary: A cli tool that will keep you in loop with your Github
Home-page: https://github.com/RohitDarekar816/gitloop
Author: Rohit Darekar
Author-email: Rohit Darekar <rohitdarekar816@gmail.com>
License-Expression: MIT
Project-URL: Homepage, https://github.com/RohitDarekar816/gitloop
Project-URL: Issues, https://github.com/RohitDarekar816/gitloop/issues
Classifier: Programming Language :: Python :: 3
Classifier: Operating System :: OS Independent
Requires-Python: >=3.6
License-File: LICENSE
Dynamic: author
Dynamic: home-page
Dynamic: license-file
Dynamic: requires-python
